[
{"id": "zhang-mingyang", "name": "Zhang Mingyang", "nickname": "Mountain Tiger", "record": {"wins": 19, "losses": 6, "draws": 0}, "wins": 19, "losses": 6, "draws": 0, "division": "", "height": "", "weight": "", "reach": "", "stance": "", "dob": "", "hometown": "", "team": "", "stats": {}, "personal_info": {}, "fight_history": [], "fighter_url": "/athlete/zhang-mingyang", "scraped_at": "2025-06-30T22:52:05.556493"},
{"id": "alonzo-menifield", "name": "Alonzo Menifield", "nickname": "Atomic", "record": {"wins": 17, "losses": 5, "draws": 1}, "wins": 17, "losses": 5, "draws": 1, "division": "", "height": "", "weight": "", "reach": "", "stance": "", "dob": "", "hometown": "", "team": "", "stats": {}, "personal_info": {}, "fight_history": [], "fighter_url": "/athlete/alonzo-menifield", "scraped_at": "2025-06-30T22:52:05.571006"},
{"id": "ciryl-gane", "name": "Ciryl Gane", "nickname": "Bon Gamin", "record": {"wins": 13, "losses": 2, "draws": 0}, "wins": 13, "losses": 2, "draws": 0, "division": "", "height": "", "weight": "", "reach": "", "stance": "", "dob": "", "hometown": "", "team": "", "stats": {}, "personal_info": {}, "fight_history": [], "fighter_url": "/athlete/ciryl-gane", "scraped_at": "2025-06-30T22:52:05.587635"},
{"id": "alexander-volkov", "name": "Alexander Volkov", "nickname": "Drago", "record": {"wins": 38, "losses": 11, "draws": 0}, "wins": 38, "losses": 11, "draws": 0, "division": "", "height": "", "weight": "", "reach": "", "stance": "", "dob": "", "hometown": "", "team": "", "stats": {}, "personal_info": {}, "fight_history": [], "fighter_url": "/athlete/alexander-volkov", "scraped_at": "2025-06-30T22:52:05.601323"},
{"id": "sergei-pavlovich", "name": "Sergei Pavlovich", "nickname": "", "record": {"wins": 19, "losses": 3, "draws": 0}, "wins": 19, "losses": 3, "draws": 0, "division": "", "height": "", "weight": "", "reach": "", "stance": "", "dob": "", "hometown": "", "team": "", "stats": {}, "personal_info": {}, "fight_history": [], "fighter_url": "/athlete/sergei-pavlovich", "scraped_at": "2025-06-30T22:52:05.614579"},
{"id": "curtis-blaydes", "name": "Curtis Blaydes", "nickname": "Razor", "record": {"wins": 19, "losses": 5, "draws": 0}, "wins": 19, "losses": 5, "draws": 0, "division": "", "height": "", "weight": "", "reach": "", "stance": "", "dob": "", "hometown": "", "team": "", "stats": {}, "personal_info": {}, "fight_history": [], "fighter_url": "/athlete/curtis-blaydes", "scraped_at": "2025-06-30T22:52:05.628034"},
{"id": "jailton-almeida", "name": "Jailton Almeida", "nickname": "Malhadinho", "record": {"wins": 22, "losses": 3, "draws": 0}, "wins": 22, "losses": 3, "draws": 0, "division": "", "height": "", "weight": "", "reach": "", "stance": "", "dob": "", "hometown": "", "team": "", "stats": {}, "personal_info": {}, "fight_history": [], "fighter_url": "/athlete/jailton-almeida", "scraped_at": "2025-06-30T22:52:05.641794"},
{"id": "waldo-cortes-acosta", "name": "Waldo Cortes Acosta", "nickname": "Salsa Boy", "record": {"wins": 14, "losses": 1, "draws": 0}, "wins": 14, "losses": 1, "draws": 0, "division": "", "height": "", "weight": "", "reach": "", "stance": "", "dob": "", "hometown": "", "team": "", "stats": {}, "personal_info": {}, "fight_history": [], "fighter_url": "/athlete/waldo-cortes-acosta", "scraped_at": "2025-06-30T22:52:05.655837"},
{"id": "marcin-tybura", "name": "Marcin Tybura", "nickname": "Tybur", "record": {"wins": 27, "losses": 9, "draws": 0}, "wins": 27, "losses": 9, "draws": 0, "division": "", "height": "", "weight": "", "reach": "", "stance": "", "dob": "", "hometown": "", "team": "", "stats": {}, "personal_info": {}, "fight_history": [], "fighter_url": "/athlete/marcin-tybura", "scraped_at": "2025-06-30T22:52:05.669906"},
{"id": "serghei-spivac", "name": "Serghei Spivac", "nickname": "Polar Bear", "record": {"wins": 17, "losses": 6, "draws": 0}, "wins": 17, "losses": 6, "draws": 0, "division": "", "height": "", "weight": "", "reach": "", "stance": "", "dob": "", "hometown": "", "team": "", "stats": {}, "personal_info": {}, "fight_history": [], "fighter_url": "/athlete/serghei-spivac", "scraped_at": "2025-06-30T22:52:05.683928"}
]