[
{"id": "manon-fiorot", "name": "Manon Fiorot", "nickname": "The Beast", "record": {"wins": 12, "losses": 2, "draws": 0}, "wins": 12, "losses": 2, "draws": 0, "division": "", "height": "", "weight": "", "reach": "", "stance": "", "dob": "", "hometown": "", "team": "", "stats": {}, "personal_info": {}, "fight_history": [], "fighter_url": "/athlete/manon-fiorot", "scraped_at": "2025-06-30T22:52:12.854263"},
{"id": "julianna-pena", "name": "Julianna Peña", "nickname": "The Venezuelan Vixen", "record": {"wins": 13, "losses": 6, "draws": 0}, "wins": 13, "losses": 6, "draws": 0, "division": "", "height": "", "weight": "", "reach": "", "stance": "", "dob": "", "hometown": "", "team": "", "stats": {}, "personal_info": {}, "fight_history": [], "fighter_url": "/athlete/julianna-pena", "scraped_at": "2025-06-30T22:52:12.871801"},
{"id": "natalia-silva", "name": "Natalia Silva", "nickname": "", "record": {"wins": 19, "losses": 5, "draws": 1}, "wins": 19, "losses": 5, "draws": 1, "division": "", "height": "", "weight": "", "reach": "", "stance": "", "dob": "", "hometown": "", "team": "", "stats": {}, "personal_info": {}, "fight_history": [], "fighter_url": "/athlete/natalia-silva", "scraped_at": "2025-06-30T22:52:12.886930"},
{"id": "alexa-grasso", "name": "Alexa Grasso", "nickname": "", "record": {"wins": 16, "losses": 5, "draws": 1}, "wins": 16, "losses": 5, "draws": 1, "division": "", "height": "", "weight": "", "reach": "", "stance": "", "dob": "", "hometown": "", "team": "", "stats": {}, "personal_info": {}, "fight_history": [], "fighter_url": "/athlete/alexa-grasso", "scraped_at": "2025-06-30T22:52:12.901152"},
{"id": "erin-blanchfield", "name": "Erin Blanchfield", "nickname": "Cold Blooded", "record": {"wins": 13, "losses": 2, "draws": 0}, "wins": 13, "losses": 2, "draws": 0, "division": "", "height": "", "weight": "", "reach": "", "stance": "", "dob": "", "hometown": "", "team": "", "stats": {}, "personal_info": {}, "fight_history": [], "fighter_url": "/athlete/erin-blanchfield", "scraped_at": "2025-06-30T22:52:12.915592"},
{"id": "virna-jandiroba", "name": "Virna Jandiroba", "nickname": "Carcara", "record": {"wins": 22, "losses": 3, "draws": 0}, "wins": 22, "losses": 3, "draws": 0, "division": "", "height": "", "weight": "", "reach": "", "stance": "", "dob": "", "hometown": "", "team": "", "stats": {}, "personal_info": {}, "fight_history": [], "fighter_url": "/athlete/virna-jandiroba", "scraped_at": "2025-06-30T22:52:12.929779"},
{"id": "raquel-pennington", "name": "Raquel Pennington", "nickname": "Rocky", "record": {"wins": 16, "losses": 10, "draws": 0}, "wins": 16, "losses": 10, "draws": 0, "division": "", "height": "", "weight": "", "reach": "", "stance": "", "dob": "", "hometown": "", "team": "", "stats": {}, "personal_info": {}, "fight_history": [], "fighter_url": "/athlete/raquel-pennington", "scraped_at": "2025-06-30T22:52:12.944006"},
{"id": "tatiana-suarez", "name": "Tatiana Suarez", "nickname": "", "record": {"wins": 11, "losses": 1, "draws": 0}, "wins": 11, "losses": 1, "draws": 0, "division": "", "height": "", "weight": "", "reach": "", "stance": "", "dob": "", "hometown": "", "team": "", "stats": {}, "personal_info": {}, "fight_history": [], "fighter_url": "/athlete/tatiana-suarez", "scraped_at": "2025-06-30T22:52:12.962373"},
{"id": "rose-namajunas", "name": "Rose Namajunas", "nickname": "Thug", "record": {"wins": 15, "losses": 7, "draws": 0}, "wins": 15, "losses": 7, "draws": 0, "division": "", "height": "", "weight": "", "reach": "", "stance": "", "dob": "", "hometown": "", "team": "", "stats": {}, "personal_info": {}, "fight_history": [], "fighter_url": "/athlete/rose-namajunas", "scraped_at": "2025-06-30T22:52:12.979087"},
{"id": "xiaonan-yan", "name": "Yan Xiaonan", "nickname": "", "record": {"wins": 19, "losses": 5, "draws": 0}, "wins": 19, "losses": 5, "draws": 0, "division": "", "height": "", "weight": "", "reach": "", "stance": "", "dob": "", "hometown": "", "team": "", "stats": {}, "personal_info": {}, "fight_history": [], "fighter_url": "/athlete/xiaonan-yan", "scraped_at": "2025-06-30T22:52:12.993938"}
]