[
{"id": "stephen-thompson", "name": "Stephen Thompson", "nickname": "Wonderboy", "record": {"wins": 17, "losses": 8, "draws": 1}, "wins": 17, "losses": 8, "draws": 1, "division": "", "height": "", "weight": "", "reach": "", "stance": "", "dob": "", "hometown": "", "team": "", "stats": {}, "personal_info": {}, "fight_history": [], "fighter_url": "/athlete/stephen-thompson", "scraped_at": "2025-06-30T22:51:54.647889"},
{"id": "carlos-prates", "name": "Carlos Prates", "nickname": "The Nightmare", "record": {"wins": 21, "losses": 7, "draws": 0}, "wins": 21, "losses": 7, "draws": 0, "division": "", "height": "", "weight": "", "reach": "", "stance": "", "dob": "", "hometown": "", "team": "", "stats": {}, "personal_info": {}, "fight_history": [], "fighter_url": "/athlete/carlos-prates", "scraped_at": "2025-06-30T22:51:54.663862"},
{"id": "kevin-holland", "name": "Kevin Holland", "nickname": "Trailblazer", "record": {"wins": 28, "losses": 13, "draws": 0}, "wins": 28, "losses": 13, "draws": 0, "division": "", "height": "", "weight": "", "reach": "", "stance": "", "dob": "", "hometown": "", "team": "", "stats": {}, "personal_info": {}, "fight_history": [], "fighter_url": "/athlete/kevin-holland", "scraped_at": "2025-06-30T22:51:54.682208"},
{"id": "michael-page", "name": "Michael Page", "nickname": "Venom", "record": {"wins": 23, "losses": 3, "draws": 0}, "wins": 23, "losses": 3, "draws": 0, "division": "", "height": "", "weight": "", "reach": "", "stance": "", "dob": "", "hometown": "", "team": "", "stats": {}, "personal_info": {}, "fight_history": [], "fighter_url": "/athlete/michael-page", "scraped_at": "2025-06-30T22:51:54.696795"},
{"id": "nassourdine-imavov", "name": "Nassourdine Imavov", "nickname": "The Sniper", "record": {"wins": 16, "losses": 4, "draws": 0}, "wins": 16, "losses": 4, "draws": 0, "division": "", "height": "", "weight": "", "reach": "", "stance": "", "dob": "", "hometown": "", "team": "", "stats": {}, "personal_info": {}, "fight_history": [], "fighter_url": "/athlete/nassourdine-imavov", "scraped_at": "2025-06-30T22:51:54.711127"},
{"id": "sean-strickland", "name": "Sean Strickland", "nickname": "", "record": {"wins": 29, "losses": 7, "draws": 0}, "wins": 29, "losses": 7, "draws": 0, "division": "", "height": "", "weight": "", "reach": "", "stance": "", "dob": "", "hometown": "", "team": "", "stats": {}, "personal_info": {}, "fight_history": [], "fighter_url": "/athlete/sean-strickland", "scraped_at": "2025-06-30T22:51:54.726051"},
{"id": "israel-adesanya", "name": "Israel Adesanya", "nickname": "The Last Stylebender", "record": {"wins": 24, "losses": 5, "draws": 0}, "wins": 24, "losses": 5, "draws": 0, "division": "", "height": "", "weight": "", "reach": "", "stance": "", "dob": "", "hometown": "", "team": "", "stats": {}, "personal_info": {}, "fight_history": [], "fighter_url": "/athlete/israel-adesanya", "scraped_at": "2025-06-30T22:51:54.740644"},
{"id": "robert-whittaker", "name": "Robert Whittaker", "nickname": "The Reaper", "record": {"wins": 27, "losses": 8, "draws": 0}, "wins": 27, "losses": 8, "draws": 0, "division": "", "height": "", "weight": "", "reach": "", "stance": "", "dob": "", "hometown": "", "team": "", "stats": {}, "personal_info": {}, "fight_history": [], "fighter_url": "/athlete/robert-whittaker", "scraped_at": "2025-06-30T22:51:54.755327"},
{"id": "caio-borralho", "name": "Caio Borralho", "nickname": "The Natural", "record": {"wins": 17, "losses": 1, "draws": 0}, "wins": 17, "losses": 1, "draws": 0, "division": "", "height": "", "weight": "", "reach": "", "stance": "", "dob": "", "hometown": "", "team": "", "stats": {}, "personal_info": {}, "fight_history": [], "fighter_url": "/athlete/caio-borralho", "scraped_at": "2025-06-30T22:51:54.770211"},
{"id": "jared-cannonier", "name": "Jared Cannonier", "nickname": "Tha Killa Gorilla", "record": {"wins": 18, "losses": 8, "draws": 0}, "wins": 18, "losses": 8, "draws": 0, "division": "", "height": "", "weight": "", "reach": "", "stance": "", "dob": "", "hometown": "", "team": "", "stats": {}, "personal_info": {}, "fight_history": [], "fighter_url": "/athlete/jared-cannonier", "scraped_at": "2025-06-30T22:51:54.785610"}
]